Metadata-Version: 2.1
Name: PyFormManager
Version: 1.0.0
Summary: Py_Form
Home-page: UNKNOWN
Author: qrobles
Author-email: botnar.ivan02@mail.ru
License: UNKNOWN
Platform: UNKNOWN
